Metadata-Version: 2.1
Name: overview-plugin-workqueue
Version: 1.0.1
Summary: In-process work queue for use in Overview plugins
Home-page: https://github.com/overview/py-plugin-workqueue
Author: Adam Hooper
Author-email: adam@adamhooper.com
License: UNKNOWN
Platform: UNKNOWN
Classifier: Programming Language :: Python :: 3
Classifier: License :: OSI Approved :: MIT License
Classifier: Operating System :: OS Independent
